README.md
setup.py
imagepreprocessing/__cfg_templates.py
imagepreprocessing/__convert_annotations.py
imagepreprocessing/__file_operations.py
imagepreprocessing/__init__.py
imagepreprocessing/__other_functions.py
imagepreprocessing/darknet_functions.py
imagepreprocessing/imagepreprocessing.py
imagepreprocessing/keras_functions.py
imagepreprocessing/utilities.py
imagepreprocessing.egg-info/PKG-INFO
imagepreprocessing.egg-info/SOURCES.txt
imagepreprocessing.egg-info/dependency_links.txt
imagepreprocessing.egg-info/top_level.txt