Metadata-Version: 2.1
Name: imagepreprocessing
Version: 1.7.2
Summary: image preprocessing
Home-page: https://github.com/cccaaannn/imagepreprocessing
Author: Can Kurt
Author-email: can.kurt.aa@gmail.com
License: UNKNOWN
Platform: UNKNOWN
Classifier: Programming Language :: Python :: 3
Classifier: License :: OSI Approved :: MIT License
Classifier: Operating System :: OS Independent
